<?xml version="1.0" encoding="UTF-8"?>
<TVAMain xmlns="urn:tva:metadata:2007" xmlns:mpeg7="urn:tva:mpeg7:2005"
xml:lang="ENG"> <ProgramDescription> <ProgramLocationTable> <Schedule
serviceIDRef="741.imagenio.es" Version="0"> <ScheduleEvent> <Program
crid="crid://imagenio.es/0/39932192/39932192" /> <InstanceDescription> <Title>Los
nº1 de los 40 Principales</Title> <Genre
href="urn:miviewtv:cs:GenreCS:2007:96.104"> <Name>Actual</Name> </Genre> <ParentalGuidance>
<mpeg7:ParentalRating
href="urn:dvb:metadata:cs:ParentalGuidanceCS:2007:2"> <mpeg7:Name>Suitable
for all audiences</mpeg7:Name> </mpeg7:ParentalRating> </ParentalGuidance>
</InstanceDescription> <PublishedStartTime>2015-04-02T03:00:00.000Z</PublishedStartTime>
<PublishedDuration>PT1H</PublishedDuration> <ImmediateViewing
value="false" /> <NetworkRecordOperator>default|STOVER</NetworkRecordOperator>
<UserActionList> <mpeg7:ActionType> <mpeg7:Name>FastForward</mpeg7:Name> </mpeg7:ActionType>
</UserActionList> <EventStartTime>2015-04-02T03:00:00.000Z</EventStartTime>
<EventDuration>PT1H</EventDuration> </ScheduleEvent> <ScheduleEvent> <Program
crid="crid://imagenio.es/0/39932193/39932193" /> <InstanceDescription> <Title>Fórmula
40</Title> <Genre href="urn:miviewtv:cs:GenreCS:2007:96.104"> <Name>Actual</Name>
</Genre> <ParentalGuidance> <mpeg7:ParentalRating
href="urn:dvb:metadata:cs:ParentalGuidanceCS:2007:2"> <mpeg7:Name>Suitable
for all audiences</mpeg7:Name> </mpeg7:ParentalRating> </ParentalGuidance>
</InstanceDescription> <PublishedStartTime>2015-04-02T04:00:00.000Z</PublishedStartTime>
<PublishedDuration>PT2H30M</PublishedDuration> <ImmediateViewing
value="false" /> <NetworkRecordOperator>default|STOVER</NetworkRecordOperator>
<UserActionList> <mpeg7:ActionType> <mpeg7:Name>FastForward</mpeg7:Name> </mpeg7:ActionType>
</UserActionList> <EventStartTime>2015-04-02T04:00:00.000Z</EventStartTime>
<EventDuration>PT2H30M</EventDuration> </ScheduleEvent> <ScheduleEvent> <Program
crid="crid://imagenio.es/0/39932194/39932194" /> <InstanceDescription> <Title>Del
40 al 1 Xpres</Title> <Genre href="urn:miviewtv:cs:GenreCS:2007:96.104"> <Name>Actual</Name>
</Genre> <ParentalGuidance> <mpeg7:ParentalRating
href="urn:dvb:metadata:cs:ParentalGuidanceCS:2007:2"> <mpeg7:Name>Suitable
for all audiences</mpeg7:Name> </mpeg7:ParentalRating> </ParentalGuidance>
</InstanceDescription> <PublishedStartTime>2015-04-02T06:30:00.000Z</PublishedStartTime>
<PublishedDuration>PT30M</PublishedDuration> <ImmediateViewing
value="false" /> <NetworkRecordOperator>default|STOVER</NetworkRecordOperator>
<UserActionList> <mpeg7:ActionType> <mpeg7:Name>FastForward</mpeg7:Name> </mpeg7:ActionType>
</UserActionList> <EventStartTime>2015-04-02T06:30:00.000Z</EventStartTime>
<EventDuration>PT30M</EventDuration> </ScheduleEvent> <ScheduleEvent> <Program
crid="crid://imagenio.es/0/39932195/39932195" /> <InstanceDescription> <Title>40
Latino</Title> <Genre href="urn:miviewtv:cs:GenreCS:2007:96.104"> <Name>Actual</Name>
</Genre> <ParentalGuidance> <mpeg7:ParentalRating
href="urn:dvb:metadata:cs:ParentalGuidanceCS:2007:2"> <mpeg7:Name>Suitable
for all audiences</mpeg7:Name> </mpeg7:ParentalRating> </ParentalGuidance>
</InstanceDescription> <PublishedStartTime>2015-04-02T07:00:00.000Z</PublishedStartTime>
<PublishedDuration>PT3H</PublishedDuration> <ImmediateViewing
value="false" /> <NetworkRecordOperator>default|STOVER</NetworkRecordOperator>
<UserActionList> <mpeg7:ActionType> <mpeg7:Name>FastForward</mpeg7:Name> </mpeg7:ActionType>
</UserActionList> <EventStartTime>2015-04-02T07:00:00.000Z</EventStartTime>
<EventDuration>PT3H</EventDuration> </ScheduleEvent> <ScheduleEvent> <Program
crid="crid://imagenio.es/0/39932196/39932196" /> <InstanceDescription> <Title>Fórmula
40</Title> <Genre href="urn:miviewtv:cs:GenreCS:2007:96.104"> <Name>Actual</Name>
</Genre> <ParentalGuidance> <mpeg7:ParentalRating
href="urn:dvb:metadata:cs:ParentalGuidanceCS:2007:2"> <mpeg7:Name>Suitable
for all audiences</mpeg7:Name> </mpeg7:ParentalRating> </ParentalGuidance>
</InstanceDescription> <PublishedStartTime>2015-04-02T10:00:00.000Z</PublishedStartTime>
<PublishedDuration>PT1H30M</PublishedDuration> <ImmediateViewing
value="false" /> <NetworkRecordOperator>default|STOVER</NetworkRecordOperator>
<UserActionList> <mpeg7:ActionType> <mpeg7:Name>FastForward</mpeg7:Name> </mpeg7:ActionType>
</UserActionList> <EventStartTime>2015-04-02T10:00:00.000Z</EventStartTime>
<EventDuration>PT1H30M</EventDuration> </ScheduleEvent> <ScheduleEvent> <Program
crid="crid://imagenio.es/0/39932197/39932197" /> <InstanceDescription> <Title>Del
40 al 1 Xpres</Title> <Genre href="urn:miviewtv:cs:GenreCS:2007:96.104"> <Name>Actual</Name>
</Genre> <ParentalGuidance> <mpeg7:ParentalRating
href="urn:dvb:metadata:cs:ParentalGuidanceCS:2007:2"> <mpeg7:Name>Suitable
for all audiences</mpeg7:Name> </mpeg7:ParentalRating> </ParentalGuidance>
</InstanceDescription> <PublishedStartTime>2015-04-02T11:30:00.000Z</PublishedStartTime>
<PublishedDuration>PT30M</PublishedDuration> <ImmediateViewing
value="false" /> <NetworkRecordOperator>default|STOVER</NetworkRecordOperator>
<UserActionList> <mpeg7:ActionType> <mpeg7:Name>FastForward</mpeg7:Name> </mpeg7:ActionType>
</UserActionList> <EventStartTime>2015-04-02T11:30:00.000Z</EventStartTime>
<EventDuration>PT30M</EventDuration> </ScheduleEvent> <ScheduleEvent> <Program
crid="crid://imagenio.es/0/39932198/39932198" /> <InstanceDescription> <Title>Fórmula
40</Title> <Genre href="urn:miviewtv:cs:GenreCS:2007:96.104"> <Name>Actual</Name>
</Genre> <ParentalGuidance> <mpeg7:ParentalRating
href="urn:dvb:metadata:cs:ParentalGuidanceCS:2007:2"> <mpeg7:Name>Suitable
for all audiences</mpeg7:Name> </mpeg7:ParentalRating> </ParentalGuidance>
</InstanceDescription> <PublishedStartTime>2015-04-02T12:00:00.000Z</PublishedStartTime>
<PublishedDuration>PT4H</PublishedDuration> <ImmediateViewing
value="false" /> <NetworkRecordOperator>default|STOVER</NetworkRecordOperator>
<UserActionList> <mpeg7:ActionType> <mpeg7:Name>FastForward</mpeg7:Name> </mpeg7:ActionType>
</UserActionList> <EventStartTime>2015-04-02T12:00:00.000Z</EventStartTime>
<EventDuration>PT4H</EventDuration> </ScheduleEvent> <ScheduleEvent> <Program
crid="crid://imagenio.es/0/39932199/39932199" /> <InstanceDescription> <Title>Del
40 al 1 Xpres</Title> <Genre href="urn:miviewtv:cs:GenreCS:2007:96.104"> <Name>Actual</Name>
</Genre> <ParentalGuidance> <mpeg7:ParentalRating
href="urn:dvb:metadata:cs:ParentalGuidanceCS:2007:2"> <mpeg7:Name>Suitable
for all audiences</mpeg7:Name> </mpeg7:ParentalRating> </ParentalGuidance>
</InstanceDescription> <PublishedStartTime>2015-04-02T16:00:00.000Z</PublishedStartTime>
<PublishedDuration>PT30M</PublishedDuration> <ImmediateViewing
value="false" /> <NetworkRecordOperator>default|STOVER</NetworkRecordOperator>
<UserActionList> <mpeg7:ActionType> <mpeg7:Name>FastForward</mpeg7:Name> </mpeg7:ActionType>
</UserActionList> <EventStartTime>2015-04-02T16:00:00.000Z</EventStartTime>
<EventDuration>PT30M</EventDuration> </ScheduleEvent> <ScheduleEvent> <Program
crid="crid://imagenio.es/0/39932200/39932200" /> <InstanceDescription> <Title>Fórmula
40</Title> <Genre href="urn:miviewtv:cs:GenreCS:2007:96.104"> <Name>Actual</Name>
</Genre> <ParentalGuidance> <mpeg7:ParentalRating
href="urn:dvb:metadata:cs:ParentalGuidanceCS:2007:2"> <mpeg7:Name>Suitable
for all audiences</mpeg7:Name> </mpeg7:ParentalRating> </ParentalGuidance>
</InstanceDescription> <PublishedStartTime>2015-04-02T16:30:00.000Z</PublishedStartTime>
<PublishedDuration>PT2H30M</PublishedDuration> <ImmediateViewing
value="false" /> <NetworkRecordOperator>default|STOVER</NetworkRecordOperator>
<UserActionList> <mpeg7:ActionType> <mpeg7:Name>FastForward</mpeg7:Name> </mpeg7:ActionType>
</UserActionList> <EventStartTime>2015-04-02T16:30:00.000Z</EventStartTime>
<EventDuration>PT2H30M</EventDuration> </ScheduleEvent> <ScheduleEvent> <Program
crid="crid://imagenio.es/0/39932201/39932201" /> <InstanceDescription> <Title>Los
nº1 de los 40 Principales</Title> <Genre
href="urn:miviewtv:cs:GenreCS:2007:96.104"> <Name>Actual</Name> </Genre> <ParentalGuidance>
<mpeg7:ParentalRating
href="urn:dvb:metadata:cs:ParentalGuidanceCS:2007:2"> <mpeg7:Name>Suitable
for all audiences</mpeg7:Name> </mpeg7:ParentalRating> </ParentalGuidance>
</InstanceDescription> <PublishedStartTime>2015-04-02T19:00:00.000Z</PublishedStartTime>
<PublishedDuration>PT1H</PublishedDuration> <ImmediateViewing
value="false" /> <NetworkRecordOperator>default|STOVER</NetworkRecordOperator>
<UserActionList> <mpeg7:ActionType> <mpeg7:Name>FastForward</mpeg7:Name> </mpeg7:ActionType>
</UserActionList> <EventStartTime>2015-04-02T19:00:00.000Z</EventStartTime>
<EventDuration>PT1H</EventDuration> </ScheduleEvent> <ScheduleEvent> <Program
crid="crid://imagenio.es/0/39932202/39932202" /> <InstanceDescription> <Title>40
Classic</Title> <Genre href="urn:miviewtv:cs:GenreCS:2007:96.104"> <Name>Actual</Name>
</Genre> <ParentalGuidance> <mpeg7:ParentalRating
href="urn:dvb:metadata:cs:ParentalGuidanceCS:2007:2"> <mpeg7:Name>Suitable
for all audiences</mpeg7:Name> </mpeg7:ParentalRating> </ParentalGuidance>
</InstanceDescription> <PublishedStartTime>2015-04-02T20:00:00.000Z</PublishedStartTime>
<PublishedDuration>PT3H</PublishedDuration> <ImmediateViewing
value="false" /> <NetworkRecordOperator>default|STOVER</NetworkRecordOperator>
<UserActionList> <mpeg7:ActionType> <mpeg7:Name>FastForward</mpeg7:Name> </mpeg7:ActionType>
</UserActionList> <EventStartTime>2015-04-02T20:00:00.000Z</EventStartTime>
<EventDuration>PT3H</EventDuration> </ScheduleEvent> <ScheduleEvent> <Program
crid="crid://imagenio.es/0/39932203/39932203" /> <InstanceDescription> <Title>Fórmula
40</Title> <Genre href="urn:miviewtv:cs:GenreCS:2007:96.104"> <Name>Actual</Name>
</Genre> <ParentalGuidance> <mpeg7:ParentalRating
href="urn:dvb:metadata:cs:ParentalGuidanceCS:2007:2"> <mpeg7:Name>Suitable
for all audiences</mpeg7:Name> </mpeg7:ParentalRating> </ParentalGuidance>
</InstanceDescription> <PublishedStartTime>2015-04-02T23:00:00.000Z</PublishedStartTime>
<PublishedDuration>PT4H</PublishedDuration> <ImmediateViewing
value="false" /> <NetworkRecordOperator>default|STOVER</NetworkRecordOperator>
<UserActionList> <mpeg7:ActionType> <mpeg7:Name>FastForward</mpeg7:Name> </mpeg7:ActionType>
</UserActionList> <EventStartTime>2015-04-02T23:00:00.000Z</EventStartTime>
<EventDuration>PT4H</EventDuration> </ScheduleEvent> </Schedule> </ProgramLocationTable>
</ProgramDescription> </TVAMain>