<?xml version="1.0" encoding="UTF-8"?>
<TVAMain xmlns="urn:tva:metadata:2007" xmlns:mpeg7="urn:tva:mpeg7:2005"
xml:lang="ENG"> <ProgramDescription> <ProgramLocationTable> <Schedule
serviceIDRef="22.imagenio.es" Version="0"> <ScheduleEvent> <Program
crid="crid://imagenio.es/0/39889836/39889836" /> <InstanceDescription> <Title>Cocina
Italiana: Episodio 22</Title> <Genre
href="urn:miviewtv:cs:GenreCS:2007:0.3"> <Name>Cocina</Name> </Genre> <ParentalGuidance>
<mpeg7:ParentalRating
href="urn:dvb:metadata:cs:ParentalGuidanceCS:2007:2"> <mpeg7:Name>Suitable
for all audiences</mpeg7:Name> </mpeg7:ParentalRating> </ParentalGuidance>
</InstanceDescription> <PublishedStartTime>2015-03-26T00:00:00.000Z</PublishedStartTime>
<PublishedDuration>PT30M</PublishedDuration> <ImmediateViewing
value="false" /> <NetworkRecordOperator>default|STOVER</NetworkRecordOperator>
<UserActionList> <mpeg7:ActionType> <mpeg7:Name>FastForward</mpeg7:Name> </mpeg7:ActionType>
</UserActionList> <EventStartTime>2015-03-26T00:00:00.000Z</EventStartTime>
<EventDuration>PT30M</EventDuration> </ScheduleEvent> <ScheduleEvent> <Program
crid="crid://imagenio.es/0/39889837/39889837" /> <InstanceDescription> <Title>Los
fogones tradicionales: Episodio 162</Title> <Genre
href="urn:miviewtv:cs:GenreCS:2007:0.3"> <Name>Cocina</Name> </Genre> <ParentalGuidance>
<mpeg7:ParentalRating
href="urn:dvb:metadata:cs:ParentalGuidanceCS:2007:2"> <mpeg7:Name>Suitable
for all audiences</mpeg7:Name> </mpeg7:ParentalRating> </ParentalGuidance>
</InstanceDescription> <PublishedStartTime>2015-03-26T00:30:00.000Z</PublishedStartTime>
<PublishedDuration>PT30M</PublishedDuration> <ImmediateViewing
value="false" /> <NetworkRecordOperator>default|STOVER</NetworkRecordOperator>
<UserActionList> <mpeg7:ActionType> <mpeg7:Name>FastForward</mpeg7:Name> </mpeg7:ActionType>
</UserActionList> <EventStartTime>2015-03-26T00:30:00.000Z</EventStartTime>
<EventDuration>PT30M</EventDuration> </ScheduleEvent> <ScheduleEvent> <Program
crid="crid://imagenio.es/0/39889838/39889838" /> <InstanceDescription> <Title>Alta
Cocina Low Cost: Episodio 18</Title> <Genre
href="urn:miviewtv:cs:GenreCS:2007:0.3"> <Name>Cocina</Name> </Genre> <ParentalGuidance>
<mpeg7:ParentalRating
href="urn:dvb:metadata:cs:ParentalGuidanceCS:2007:2"> <mpeg7:Name>Suitable
for all audiences</mpeg7:Name> </mpeg7:ParentalRating> </ParentalGuidance>
</InstanceDescription> <PublishedStartTime>2015-03-26T01:00:00.000Z</PublishedStartTime>
<PublishedDuration>PT30M</PublishedDuration> <ImmediateViewing
value="false" /> <NetworkRecordOperator>default|STOVER</NetworkRecordOperator>
<UserActionList> <mpeg7:ActionType> <mpeg7:Name>FastForward</mpeg7:Name> </mpeg7:ActionType>
</UserActionList> <EventStartTime>2015-03-26T01:00:00.000Z</EventStartTime>
<EventDuration>PT30M</EventDuration> </ScheduleEvent> <ScheduleEvent> <Program
crid="crid://imagenio.es/0/39889839/39889839" /> <InstanceDescription> <Title>Cocinamos
contigo: Episodio 377</Title> <Genre
href="urn:miviewtv:cs:GenreCS:2007:0.3"> <Name>Cocina</Name> </Genre> <ParentalGuidance>
<mpeg7:ParentalRating
href="urn:dvb:metadata:cs:ParentalGuidanceCS:2007:2"> <mpeg7:Name>Suitable
for all audiences</mpeg7:Name> </mpeg7:ParentalRating> </ParentalGuidance>
</InstanceDescription> <PublishedStartTime>2015-03-26T01:30:00.000Z</PublishedStartTime>
<PublishedDuration>PT30M</PublishedDuration> <ImmediateViewing
value="false" /> <NetworkRecordOperator>default|STOVER</NetworkRecordOperator>
<UserActionList> <mpeg7:ActionType> <mpeg7:Name>FastForward</mpeg7:Name> </mpeg7:ActionType>
</UserActionList> <EventStartTime>2015-03-26T01:30:00.000Z</EventStartTime>
<EventDuration>PT30M</EventDuration> </ScheduleEvent> <ScheduleEvent> <Program
crid="crid://imagenio.es/0/39889840/39889840" /> <InstanceDescription> <Title>El
toque de Samantha: Episodio 46</Title> <Genre
href="urn:miviewtv:cs:GenreCS:2007:0.3"> <Name>Cocina</Name> </Genre> <ParentalGuidance>
<mpeg7:ParentalRating
href="urn:dvb:metadata:cs:ParentalGuidanceCS:2007:2"> <mpeg7:Name>Suitable
for all audiences</mpeg7:Name> </mpeg7:ParentalRating> </ParentalGuidance>
</InstanceDescription> <PublishedStartTime>2015-03-26T02:00:00.000Z</PublishedStartTime>
<PublishedDuration>PT30M</PublishedDuration> <ImmediateViewing
value="false" /> <NetworkRecordOperator>default|STOVER</NetworkRecordOperator>
<UserActionList> <mpeg7:ActionType> <mpeg7:Name>FastForward</mpeg7:Name> </mpeg7:ActionType>
</UserActionList> <EventStartTime>2015-03-26T02:00:00.000Z</EventStartTime>
<EventDuration>PT30M</EventDuration> </ScheduleEvent> <ScheduleEvent> <Program
crid="crid://imagenio.es/0/39889841/39889841" /> <InstanceDescription> <Title>Los
22 minutos de Julius: Episodio 343</Title> <Genre
href="urn:miviewtv:cs:GenreCS:2007:0.3"> <Name>Cocina</Name> </Genre> <ParentalGuidance>
<mpeg7:ParentalRating
href="urn:dvb:metadata:cs:ParentalGuidanceCS:2007:2"> <mpeg7:Name>Suitable
for all audiences</mpeg7:Name> </mpeg7:ParentalRating> </ParentalGuidance>
</InstanceDescription> <PublishedStartTime>2015-03-26T02:30:00.000Z</PublishedStartTime>
<PublishedDuration>PT30M</PublishedDuration> <ImmediateViewing
value="false" /> <NetworkRecordOperator>default|STOVER</NetworkRecordOperator>
<UserActionList> <mpeg7:ActionType> <mpeg7:Name>FastForward</mpeg7:Name> </mpeg7:ActionType>
</UserActionList> <EventStartTime>2015-03-26T02:30:00.000Z</EventStartTime>
<EventDuration>PT30M</EventDuration> </ScheduleEvent> <ScheduleEvent> <Program
crid="crid://imagenio.es/0/39889842/39889842" /> <InstanceDescription> <Title>Cocina
Italiana: Episodio 13</Title> <Genre
href="urn:miviewtv:cs:GenreCS:2007:0.3"> <Name>Cocina</Name> </Genre> <ParentalGuidance>
<mpeg7:ParentalRating
href="urn:dvb:metadata:cs:ParentalGuidanceCS:2007:2"> <mpeg7:Name>Suitable
for all audiences</mpeg7:Name> </mpeg7:ParentalRating> </ParentalGuidance>
</InstanceDescription> <PublishedStartTime>2015-03-26T03:00:00.000Z</PublishedStartTime>
<PublishedDuration>PT30M</PublishedDuration> <ImmediateViewing
value="false" /> <NetworkRecordOperator>default|STOVER</NetworkRecordOperator>
<UserActionList> <mpeg7:ActionType> <mpeg7:Name>FastForward</mpeg7:Name> </mpeg7:ActionType>
</UserActionList> <EventStartTime>2015-03-26T03:00:00.000Z</EventStartTime>
<EventDuration>PT30M</EventDuration> </ScheduleEvent> <ScheduleEvent> <Program
crid="crid://imagenio.es/0/39894583/39894583" /> <InstanceDescription> <Title>Cocinamos
contigo: Episodio 377</Title> <Genre
href="urn:miviewtv:cs:GenreCS:2007:0.3"> <Name>Cocina</Name> </Genre> <ParentalGuidance>
<mpeg7:ParentalRating
href="urn:dvb:metadata:cs:ParentalGuidanceCS:2007:2"> <mpeg7:Name>Suitable
for all audiences</mpeg7:Name> </mpeg7:ParentalRating> </ParentalGuidance>
</InstanceDescription> <PublishedStartTime>2015-03-26T03:30:00.000Z</PublishedStartTime>
<PublishedDuration>PT30M</PublishedDuration> <ImmediateViewing
value="false" /> <NetworkRecordOperator>default|STOVER</NetworkRecordOperator>
<UserActionList> <mpeg7:ActionType> <mpeg7:Name>FastForward</mpeg7:Name> </mpeg7:ActionType>
</UserActionList> <EventStartTime>2015-03-26T03:30:00.000Z</EventStartTime>
<EventDuration>PT30M</EventDuration> </ScheduleEvent> <ScheduleEvent> <Program
crid="crid://imagenio.es/0/39894584/39894584" /> <InstanceDescription> <Title>El
toque de Samantha: Episodio 46</Title> <Genre
href="urn:miviewtv:cs:GenreCS:2007:0.3"> <Name>Cocina</Name> </Genre> <ParentalGuidance>
<mpeg7:ParentalRating
href="urn:dvb:metadata:cs:ParentalGuidanceCS:2007:2"> <mpeg7:Name>Suitable
for all audiences</mpeg7:Name> </mpeg7:ParentalRating> </ParentalGuidance>
</InstanceDescription> <PublishedStartTime>2015-03-26T04:00:00.000Z</PublishedStartTime>
<PublishedDuration>PT30M</PublishedDuration> <ImmediateViewing
value="false" /> <NetworkRecordOperator>default|STOVER</NetworkRecordOperator>
<UserActionList> <mpeg7:ActionType> <mpeg7:Name>FastForward</mpeg7:Name> </mpeg7:ActionType>
</UserActionList> <EventStartTime>2015-03-26T04:00:00.000Z</EventStartTime>
<EventDuration>PT30M</EventDuration> </ScheduleEvent> <ScheduleEvent> <Program
crid="crid://imagenio.es/0/39894585/39894585" /> <InstanceDescription> <Title>Los
22 minutos de Julius: Episodio 343</Title> <Genre
href="urn:miviewtv:cs:GenreCS:2007:0.3"> <Name>Cocina</Name> </Genre> <ParentalGuidance>
<mpeg7:ParentalRating
href="urn:dvb:metadata:cs:ParentalGuidanceCS:2007:2"> <mpeg7:Name>Suitable
for all audiences</mpeg7:Name> </mpeg7:ParentalRating> </ParentalGuidance>
</InstanceDescription> <PublishedStartTime>2015-03-26T04:30:00.000Z</PublishedStartTime>
<PublishedDuration>PT30M</PublishedDuration> <ImmediateViewing
value="false" /> <NetworkRecordOperator>default|STOVER</NetworkRecordOperator>
<UserActionList> <mpeg7:ActionType> <mpeg7:Name>FastForward</mpeg7:Name> </mpeg7:ActionType>
</UserActionList> <EventStartTime>2015-03-26T04:30:00.000Z</EventStartTime>
<EventDuration>PT30M</EventDuration> </ScheduleEvent> <ScheduleEvent> <Program
crid="crid://imagenio.es/0/39894586/39894586" /> <InstanceDescription> <Title>Cocina
Italiana: Episodio 13</Title> <Genre
href="urn:miviewtv:cs:GenreCS:2007:0.3"> <Name>Cocina</Name> </Genre> <ParentalGuidance>
<mpeg7:ParentalRating
href="urn:dvb:metadata:cs:ParentalGuidanceCS:2007:2"> <mpeg7:Name>Suitable
for all audiences</mpeg7:Name> </mpeg7:ParentalRating> </ParentalGuidance>
</InstanceDescription> <PublishedStartTime>2015-03-26T05:00:00.000Z</PublishedStartTime>
<PublishedDuration>PT30M</PublishedDuration> <ImmediateViewing
value="false" /> <NetworkRecordOperator>default|STOVER</NetworkRecordOperator>
<UserActionList> <mpeg7:ActionType> <mpeg7:Name>FastForward</mpeg7:Name> </mpeg7:ActionType>
</UserActionList> <EventStartTime>2015-03-26T05:00:00.000Z</EventStartTime>
<EventDuration>PT30M</EventDuration> </ScheduleEvent> <ScheduleEvent> <Program
crid="crid://imagenio.es/0/39894587/39894587" /> <InstanceDescription> <Title>Cocinamos
contigo: Episodio 377</Title> <Genre
href="urn:miviewtv:cs:GenreCS:2007:0.3"> <Name>Cocina</Name> </Genre> <ParentalGuidance>
<mpeg7:ParentalRating
href="urn:dvb:metadata:cs:ParentalGuidanceCS:2007:2"> <mpeg7:Name>Suitable
for all audiences</mpeg7:Name> </mpeg7:ParentalRating> </ParentalGuidance>
</InstanceDescription> <PublishedStartTime>2015-03-26T05:30:00.000Z</PublishedStartTime>
<PublishedDuration>PT30M</PublishedDuration> <ImmediateViewing
value="false" /> <NetworkRecordOperator>default|STOVER</NetworkRecordOperator>
<UserActionList> <mpeg7:ActionType> <mpeg7:Name>FastForward</mpeg7:Name> </mpeg7:ActionType>
</UserActionList> <EventStartTime>2015-03-26T05:30:00.000Z</EventStartTime>
<EventDuration>PT30M</EventDuration> </ScheduleEvent> <ScheduleEvent> <Program
crid="crid://imagenio.es/0/39894588/39894588" /> <InstanceDescription> <Title>El
toque de Samantha: Episodio 46</Title> <Genre
href="urn:miviewtv:cs:GenreCS:2007:0.3"> <Name>Cocina</Name> </Genre> <ParentalGuidance>
<mpeg7:ParentalRating
href="urn:dvb:metadata:cs:ParentalGuidanceCS:2007:2"> <mpeg7:Name>Suitable
for all audiences</mpeg7:Name> </mpeg7:ParentalRating> </ParentalGuidance>
</InstanceDescription> <PublishedStartTime>2015-03-26T06:00:00.000Z</PublishedStartTime>
<PublishedDuration>PT30M</PublishedDuration> <ImmediateViewing
value="false" /> <NetworkRecordOperator>default|STOVER</NetworkRecordOperator>
<UserActionList> <mpeg7:ActionType> <mpeg7:Name>FastForward</mpeg7:Name> </mpeg7:ActionType>
</UserActionList> <EventStartTime>2015-03-26T06:00:00.000Z</EventStartTime>
<EventDuration>PT30M</EventDuration> </ScheduleEvent> <ScheduleEvent> <Program
crid="crid://imagenio.es/0/39894589/39894589" /> <InstanceDescription> <Title>Los
22 minutos de Julius: Episodio 343</Title> <Genre
href="urn:miviewtv:cs:GenreCS:2007:0.3"> <Name>Cocina</Name> </Genre> <ParentalGuidance>
<mpeg7:ParentalRating
href="urn:dvb:metadata:cs:ParentalGuidanceCS:2007:2"> <mpeg7:Name>Suitable
for all audiences</mpeg7:Name> </mpeg7:ParentalRating> </ParentalGuidance>
</InstanceDescription> <PublishedStartTime>2015-03-26T06:30:00.000Z</PublishedStartTime>
<PublishedDuration>PT30M</PublishedDuration> <ImmediateViewing
value="false" /> <NetworkRecordOperator>default|STOVER</NetworkRecordOperator>
<UserActionList> <mpeg7:ActionType> <mpeg7:Name>FastForward</mpeg7:Name> </mpeg7:ActionType>
</UserActionList> <EventStartTime>2015-03-26T06:30:00.000Z</EventStartTime>
<EventDuration>PT30M</EventDuration> </ScheduleEvent> <ScheduleEvent> <Program
crid="crid://imagenio.es/0/39894590/39894590" /> <InstanceDescription> <Title>Cocinamos
contigo: Episodio 335</Title> <Genre
href="urn:miviewtv:cs:GenreCS:2007:0.3"> <Name>Cocina</Name> </Genre> <ParentalGuidance>
<mpeg7:ParentalRating
href="urn:dvb:metadata:cs:ParentalGuidanceCS:2007:2"> <mpeg7:Name>Suitable
for all audiences</mpeg7:Name> </mpeg7:ParentalRating> </ParentalGuidance>
</InstanceDescription> <PublishedStartTime>2015-03-26T07:00:00.000Z</PublishedStartTime>
<PublishedDuration>PT30M</PublishedDuration> <ImmediateViewing
value="false" /> <NetworkRecordOperator>default|STOVER</NetworkRecordOperator>
<UserActionList> <mpeg7:ActionType> <mpeg7:Name>FastForward</mpeg7:Name> </mpeg7:ActionType>
</UserActionList> <EventStartTime>2015-03-26T07:00:00.000Z</EventStartTime>
<EventDuration>PT30M</EventDuration> </ScheduleEvent> <ScheduleEvent> <Program
crid="crid://imagenio.es/0/39894591/39894591" /> <InstanceDescription> <Title>Cocina
vasca: Episodio 24</Title> <Genre href="urn:miviewtv:cs:GenreCS:2007:0.3">
<Name>Cocina</Name> </Genre> <ParentalGuidance> <mpeg7:ParentalRating
href="urn:dvb:metadata:cs:ParentalGuidanceCS:2007:2"> <mpeg7:Name>Suitable
for all audiences</mpeg7:Name> </mpeg7:ParentalRating> </ParentalGuidance>
</InstanceDescription> <PublishedStartTime>2015-03-26T07:30:00.000Z</PublishedStartTime>
<PublishedDuration>PT30M</PublishedDuration> <ImmediateViewing
value="false" /> <NetworkRecordOperator>default|STOVER</NetworkRecordOperator>
<UserActionList> <mpeg7:ActionType> <mpeg7:Name>FastForward</mpeg7:Name> </mpeg7:ActionType>
</UserActionList> <EventStartTime>2015-03-26T07:30:00.000Z</EventStartTime>
<EventDuration>PT30M</EventDuration> </ScheduleEvent> <ScheduleEvent> <Program
crid="crid://imagenio.es/0/39894592/39894592" /> <InstanceDescription> <Title>El
toque de Samantha: Episodio 41</Title> <Genre
href="urn:miviewtv:cs:GenreCS:2007:0.3"> <Name>Cocina</Name> </Genre> <ParentalGuidance>
<mpeg7:ParentalRating
href="urn:dvb:metadata:cs:ParentalGuidanceCS:2007:2"> <mpeg7:Name>Suitable
for all audiences</mpeg7:Name> </mpeg7:ParentalRating> </ParentalGuidance>
</InstanceDescription> <PublishedStartTime>2015-03-26T08:00:00.000Z</PublishedStartTime>
<PublishedDuration>PT30M</PublishedDuration> <ImmediateViewing
value="false" /> <NetworkRecordOperator>default|STOVER</NetworkRecordOperator>
<UserActionList> <mpeg7:ActionType> <mpeg7:Name>FastForward</mpeg7:Name> </mpeg7:ActionType>
</UserActionList> <EventStartTime>2015-03-26T08:00:00.000Z</EventStartTime>
<EventDuration>PT30M</EventDuration> </ScheduleEvent> <ScheduleEvent> <Program
crid="crid://imagenio.es/0/39894593/39894593" /> <InstanceDescription> <Title>Postres
caseros: Extraña combinación</Title> <Genre
href="urn:miviewtv:cs:GenreCS:2007:0.3"> <Name>Cocina</Name> </Genre> <ParentalGuidance>
<mpeg7:ParentalRating
href="urn:dvb:metadata:cs:ParentalGuidanceCS:2007:2"> <mpeg7:Name>Suitable
for all audiences</mpeg7:Name> </mpeg7:ParentalRating> </ParentalGuidance>
</InstanceDescription> <PublishedStartTime>2015-03-26T08:30:00.000Z</PublishedStartTime>
<PublishedDuration>PT30M</PublishedDuration> <ImmediateViewing
value="false" /> <NetworkRecordOperator>default|STOVER</NetworkRecordOperator>
<UserActionList> <mpeg7:ActionType> <mpeg7:Name>FastForward</mpeg7:Name> </mpeg7:ActionType>
</UserActionList> <EventStartTime>2015-03-26T08:30:00.000Z</EventStartTime>
<EventDuration>PT30M</EventDuration> </ScheduleEvent> <ScheduleEvent> <Program
crid="crid://imagenio.es/0/39894594/39894594" /> <InstanceDescription> <Title>Cocina
Brasileña: Episodio 21</Title> <Genre
href="urn:miviewtv:cs:GenreCS:2007:0.3"> <Name>Cocina</Name> </Genre> <ParentalGuidance>
<mpeg7:ParentalRating
href="urn:dvb:metadata:cs:ParentalGuidanceCS:2007:2"> <mpeg7:Name>Suitable
for all audiences</mpeg7:Name> </mpeg7:ParentalRating> </ParentalGuidance>
</InstanceDescription> <PublishedStartTime>2015-03-26T09:00:00.000Z</PublishedStartTime>
<PublishedDuration>PT30M</PublishedDuration> <ImmediateViewing
value="false" /> <NetworkRecordOperator>default|STOVER</NetworkRecordOperator>
<UserActionList> <mpeg7:ActionType> <mpeg7:Name>FastForward</mpeg7:Name> </mpeg7:ActionType>
</UserActionList> <EventStartTime>2015-03-26T09:00:00.000Z</EventStartTime>
<EventDuration>PT30M</EventDuration> </ScheduleEvent> <ScheduleEvent> <Program
crid="crid://imagenio.es/0/39894595/39894595" /> <InstanceDescription> <Title>Pescados
y mariscos: Episodio 19</Title> <Genre
href="urn:miviewtv:cs:GenreCS:2007:0.3"> <Name>Cocina</Name> </Genre> <ParentalGuidance>
<mpeg7:ParentalRating
href="urn:dvb:metadata:cs:ParentalGuidanceCS:2007:2"> <mpeg7:Name>Suitable
for all audiences</mpeg7:Name> </mpeg7:ParentalRating> </ParentalGuidance>
</InstanceDescription> <PublishedStartTime>2015-03-26T09:30:00.000Z</PublishedStartTime>
<PublishedDuration>PT30M</PublishedDuration> <ImmediateViewing
value="false" /> <NetworkRecordOperator>default|STOVER</NetworkRecordOperator>
<UserActionList> <mpeg7:ActionType> <mpeg7:Name>FastForward</mpeg7:Name> </mpeg7:ActionType>
</UserActionList> <EventStartTime>2015-03-26T09:30:00.000Z</EventStartTime>
<EventDuration>PT30M</EventDuration> </ScheduleEvent> <ScheduleEvent> <Program
crid="crid://imagenio.es/0/39894596/39894596" /> <InstanceDescription> <Title>Recetas
francesas de Rachel Khoo: Episodio 5</Title> <Genre
href="urn:miviewtv:cs:GenreCS:2007:0.3"> <Name>Cocina</Name> </Genre> <ParentalGuidance>
<mpeg7:ParentalRating
href="urn:dvb:metadata:cs:ParentalGuidanceCS:2007:2"> <mpeg7:Name>Suitable
for all audiences</mpeg7:Name> </mpeg7:ParentalRating> </ParentalGuidance>
</InstanceDescription> <PublishedStartTime>2015-03-26T10:00:00.000Z</PublishedStartTime>
<PublishedDuration>PT30M</PublishedDuration> <ImmediateViewing
value="false" /> <NetworkRecordOperator>default|STOVER</NetworkRecordOperator>
<UserActionList> <mpeg7:ActionType> <mpeg7:Name>FastForward</mpeg7:Name> </mpeg7:ActionType>
</UserActionList> <EventStartTime>2015-03-26T10:00:00.000Z</EventStartTime>
<EventDuration>PT30M</EventDuration> </ScheduleEvent> <ScheduleEvent> <Program
crid="crid://imagenio.es/0/39894597/39894597" /> <InstanceDescription> <Title>Recetas
por 5 euros: Episodio 85</Title> <Genre
href="urn:miviewtv:cs:GenreCS:2007:0.3"> <Name>Cocina</Name> </Genre> <ParentalGuidance>
<mpeg7:ParentalRating
href="urn:dvb:metadata:cs:ParentalGuidanceCS:2007:2"> <mpeg7:Name>Suitable
for all audiences</mpeg7:Name> </mpeg7:ParentalRating> </ParentalGuidance>
</InstanceDescription> <PublishedStartTime>2015-03-26T10:30:00.000Z</PublishedStartTime>
<PublishedDuration>PT30M</PublishedDuration> <ImmediateViewing
value="false" /> <NetworkRecordOperator>default|STOVER</NetworkRecordOperator>
<UserActionList> <mpeg7:ActionType> <mpeg7:Name>FastForward</mpeg7:Name> </mpeg7:ActionType>
</UserActionList> <EventStartTime>2015-03-26T10:30:00.000Z</EventStartTime>
<EventDuration>PT30M</EventDuration> </ScheduleEvent> <ScheduleEvent> <Program
crid="crid://imagenio.es/0/39894598/39894598" /> <InstanceDescription> <Title>Cocinamos
contigo: Episodio 335</Title> <Genre
href="urn:miviewtv:cs:GenreCS:2007:0.3"> <Name>Cocina</Name> </Genre> <ParentalGuidance>
<mpeg7:ParentalRating
href="urn:dvb:metadata:cs:ParentalGuidanceCS:2007:2"> <mpeg7:Name>Suitable
for all audiences</mpeg7:Name> </mpeg7:ParentalRating> </ParentalGuidance>
</InstanceDescription> <PublishedStartTime>2015-03-26T11:00:00.000Z</PublishedStartTime>
<PublishedDuration>PT30M</PublishedDuration> <ImmediateViewing
value="false" /> <NetworkRecordOperator>default|STOVER</NetworkRecordOperator>
<UserActionList> <mpeg7:ActionType> <mpeg7:Name>FastForward</mpeg7:Name> </mpeg7:ActionType>
</UserActionList> <EventStartTime>2015-03-26T11:00:00.000Z</EventStartTime>
<EventDuration>PT30M</EventDuration> </ScheduleEvent> <ScheduleEvent> <Program
crid="crid://imagenio.es/0/39894599/39894599" /> <InstanceDescription> <Title>Dulces
con Alma: Episodio 17</Title> <Genre
href="urn:miviewtv:cs:GenreCS:2007:0.3"> <Name>Cocina</Name> </Genre> <ParentalGuidance>
<mpeg7:ParentalRating
href="urn:dvb:metadata:cs:ParentalGuidanceCS:2007:2"> <mpeg7:Name>Suitable
for all audiences</mpeg7:Name> </mpeg7:ParentalRating> </ParentalGuidance>
</InstanceDescription> <PublishedStartTime>2015-03-26T11:30:00.000Z</PublishedStartTime>
<PublishedDuration>PT30M</PublishedDuration> <ImmediateViewing
value="false" /> <NetworkRecordOperator>default|STOVER</NetworkRecordOperator>
<UserActionList> <mpeg7:ActionType> <mpeg7:Name>FastForward</mpeg7:Name> </mpeg7:ActionType>
</UserActionList> <EventStartTime>2015-03-26T11:30:00.000Z</EventStartTime>
<EventDuration>PT30M</EventDuration> </ScheduleEvent> <ScheduleEvent> <Program
crid="crid://imagenio.es/0/39894600/39894600" /> <InstanceDescription> <Title>Los
22 minutos de Julius: Episodio 361</Title> <Genre
href="urn:miviewtv:cs:GenreCS:2007:0.3"> <Name>Cocina</Name> </Genre> <ParentalGuidance>
<mpeg7:ParentalRating
href="urn:dvb:metadata:cs:ParentalGuidanceCS:2007:2"> <mpeg7:Name>Suitable
for all audiences</mpeg7:Name> </mpeg7:ParentalRating> </ParentalGuidance>
</InstanceDescription> <PublishedStartTime>2015-03-26T12:00:00.000Z</PublishedStartTime>
<PublishedDuration>PT30M</PublishedDuration> <ImmediateViewing
value="false" /> <NetworkRecordOperator>default|STOVER</NetworkRecordOperator>
<UserActionList> <mpeg7:ActionType> <mpeg7:Name>FastForward</mpeg7:Name> </mpeg7:ActionType>
</UserActionList> <EventStartTime>2015-03-26T12:00:00.000Z</EventStartTime>
<EventDuration>PT30M</EventDuration> </ScheduleEvent> <ScheduleEvent> <Program
crid="crid://imagenio.es/0/39894601/39894601" /> <InstanceDescription> <Title>Fácil
y resultón: Episodio 63</Title> <Genre
href="urn:miviewtv:cs:GenreCS:2007:0.3"> <Name>Cocina</Name> </Genre> <ParentalGuidance>
<mpeg7:ParentalRating
href="urn:dvb:metadata:cs:ParentalGuidanceCS:2007:2"> <mpeg7:Name>Suitable
for all audiences</mpeg7:Name> </mpeg7:ParentalRating> </ParentalGuidance>
</InstanceDescription> <PublishedStartTime>2015-03-26T12:30:00.000Z</PublishedStartTime>
<PublishedDuration>PT30M</PublishedDuration> <ImmediateViewing
value="false" /> <NetworkRecordOperator>default|STOVER</NetworkRecordOperator>
<UserActionList> <mpeg7:ActionType> <mpeg7:Name>FastForward</mpeg7:Name> </mpeg7:ActionType>
</UserActionList> <EventStartTime>2015-03-26T12:30:00.000Z</EventStartTime>
<EventDuration>PT30M</EventDuration> </ScheduleEvent> <ScheduleEvent> <Program
crid="crid://imagenio.es/0/39894602/39894602" /> <InstanceDescription> <Title>El
toque de Samantha: Episodio 41</Title> <Genre
href="urn:miviewtv:cs:GenreCS:2007:0.3"> <Name>Cocina</Name> </Genre> <ParentalGuidance>
<mpeg7:ParentalRating
href="urn:dvb:metadata:cs:ParentalGuidanceCS:2007:2"> <mpeg7:Name>Suitable
for all audiences</mpeg7:Name> </mpeg7:ParentalRating> </ParentalGuidance>
</InstanceDescription> <PublishedStartTime>2015-03-26T13:00:00.000Z</PublishedStartTime>
<PublishedDuration>PT30M</PublishedDuration> <ImmediateViewing
value="false" /> <NetworkRecordOperator>default|STOVER</NetworkRecordOperator>
<UserActionList> <mpeg7:ActionType> <mpeg7:Name>FastForward</mpeg7:Name> </mpeg7:ActionType>
</UserActionList> <EventStartTime>2015-03-26T13:00:00.000Z</EventStartTime>
<EventDuration>PT30M</EventDuration> </ScheduleEvent> <ScheduleEvent> <Program
crid="crid://imagenio.es/0/39894603/39894603" /> <InstanceDescription> <Title>Recetas
por 5 euros: Episodio 85</Title> <Genre
href="urn:miviewtv:cs:GenreCS:2007:0.3"> <Name>Cocina</Name> </Genre> <ParentalGuidance>
<mpeg7:ParentalRating
href="urn:dvb:metadata:cs:ParentalGuidanceCS:2007:2"> <mpeg7:Name>Suitable
for all audiences</mpeg7:Name> </mpeg7:ParentalRating> </ParentalGuidance>
</InstanceDescription> <PublishedStartTime>2015-03-26T13:30:00.000Z</PublishedStartTime>
<PublishedDuration>PT30M</PublishedDuration> <ImmediateViewing
value="false" /> <NetworkRecordOperator>default|STOVER</NetworkRecordOperator>
<UserActionList> <mpeg7:ActionType> <mpeg7:Name>FastForward</mpeg7:Name> </mpeg7:ActionType>
</UserActionList> <EventStartTime>2015-03-26T13:30:00.000Z</EventStartTime>
<EventDuration>PT30M</EventDuration> </ScheduleEvent> <ScheduleEvent> <Program
crid="crid://imagenio.es/0/39894604/39894604" /> <InstanceDescription> <Title>La
cocina natural de Annabel: Episodio 4</Title> <Genre
href="urn:miviewtv:cs:GenreCS:2007:0.3"> <Name>Cocina</Name> </Genre> <ParentalGuidance>
<mpeg7:ParentalRating
href="urn:dvb:metadata:cs:ParentalGuidanceCS:2007:2"> <mpeg7:Name>Suitable
for all audiences</mpeg7:Name> </mpeg7:ParentalRating> </ParentalGuidance>
</InstanceDescription> <PublishedStartTime>2015-03-26T14:00:00.000Z</PublishedStartTime>
<PublishedDuration>PT30M</PublishedDuration> <ImmediateViewing
value="false" /> <NetworkRecordOperator>default|STOVER</NetworkRecordOperator>
<UserActionList> <mpeg7:ActionType> <mpeg7:Name>FastForward</mpeg7:Name> </mpeg7:ActionType>
</UserActionList> <EventStartTime>2015-03-26T14:00:00.000Z</EventStartTime>
<EventDuration>PT30M</EventDuration> </ScheduleEvent> <ScheduleEvent> <Program
crid="crid://imagenio.es/0/39894605/39894605" /> <InstanceDescription> <Title>Los
fogones tradicionales: Episodio 164</Title> <Genre
href="urn:miviewtv:cs:GenreCS:2007:0.3"> <Name>Cocina</Name> </Genre> <ParentalGuidance>
<mpeg7:ParentalRating
href="urn:dvb:metadata:cs:ParentalGuidanceCS:2007:2"> <mpeg7:Name>Suitable
for all audiences</mpeg7:Name> </mpeg7:ParentalRating> </ParentalGuidance>
</InstanceDescription> <PublishedStartTime>2015-03-26T14:30:00.000Z</PublishedStartTime>
<PublishedDuration>PT30M</PublishedDuration> <ImmediateViewing
value="false" /> <NetworkRecordOperator>default|STOVER</NetworkRecordOperator>
<UserActionList> <mpeg7:ActionType> <mpeg7:Name>FastForward</mpeg7:Name> </mpeg7:ActionType>
</UserActionList> <EventStartTime>2015-03-26T14:30:00.000Z</EventStartTime>
<EventDuration>PT30M</EventDuration> </ScheduleEvent> <ScheduleEvent> <Program
crid="crid://imagenio.es/0/39894606/39894606" /> <InstanceDescription> <Title>Recetas
francesas de Rachel Khoo: Episodio 5</Title> <Genre
href="urn:miviewtv:cs:GenreCS:2007:0.3"> <Name>Cocina</Name> </Genre> <ParentalGuidance>
<mpeg7:ParentalRating
href="urn:dvb:metadata:cs:ParentalGuidanceCS:2007:2"> <mpeg7:Name>Suitable
for all audiences</mpeg7:Name> </mpeg7:ParentalRating> </ParentalGuidance>
</InstanceDescription> <PublishedStartTime>2015-03-26T15:00:00.000Z</PublishedStartTime>
<PublishedDuration>PT30M</PublishedDuration> <ImmediateViewing
value="false" /> <NetworkRecordOperator>default|STOVER</NetworkRecordOperator>
<UserActionList> <mpeg7:ActionType> <mpeg7:Name>FastForward</mpeg7:Name> </mpeg7:ActionType>
</UserActionList> <EventStartTime>2015-03-26T15:00:00.000Z</EventStartTime>
<EventDuration>PT30M</EventDuration> </ScheduleEvent> <ScheduleEvent> <Program
crid="crid://imagenio.es/0/39894607/39894607" /> <InstanceDescription> <Title>Dulces
con Alma: Episodio 17</Title> <Genre
href="urn:miviewtv:cs:GenreCS:2007:0.3"> <Name>Cocina</Name> </Genre> <ParentalGuidance>
<mpeg7:ParentalRating
href="urn:dvb:metadata:cs:ParentalGuidanceCS:2007:2"> <mpeg7:Name>Suitable
for all audiences</mpeg7:Name> </mpeg7:ParentalRating> </ParentalGuidance>
</InstanceDescription> <PublishedStartTime>2015-03-26T15:30:00.000Z</PublishedStartTime>
<PublishedDuration>PT30M</PublishedDuration> <ImmediateViewing
value="false" /> <NetworkRecordOperator>default|STOVER</NetworkRecordOperator>
<UserActionList> <mpeg7:ActionType> <mpeg7:Name>FastForward</mpeg7:Name> </mpeg7:ActionType>
</UserActionList> <EventStartTime>2015-03-26T15:30:00.000Z</EventStartTime>
<EventDuration>PT30M</EventDuration> </ScheduleEvent> <ScheduleEvent> <Program
crid="crid://imagenio.es/0/39894608/39894608" /> <InstanceDescription> <Title>Recetas
por 5 euros: Episodio 85</Title> <Genre
href="urn:miviewtv:cs:GenreCS:2007:0.3"> <Name>Cocina</Name> </Genre> <ParentalGuidance>
<mpeg7:ParentalRating
href="urn:dvb:metadata:cs:ParentalGuidanceCS:2007:2"> <mpeg7:Name>Suitable
for all audiences</mpeg7:Name> </mpeg7:ParentalRating> </ParentalGuidance>
</InstanceDescription> <PublishedStartTime>2015-03-26T16:00:00.000Z</PublishedStartTime>
<PublishedDuration>PT30M</PublishedDuration> <ImmediateViewing
value="false" /> <NetworkRecordOperator>default|STOVER</NetworkRecordOperator>
<UserActionList> <mpeg7:ActionType> <mpeg7:Name>FastForward</mpeg7:Name> </mpeg7:ActionType>
</UserActionList> <EventStartTime>2015-03-26T16:00:00.000Z</EventStartTime>
<EventDuration>PT30M</EventDuration> </ScheduleEvent> <ScheduleEvent> <Program
crid="crid://imagenio.es/0/39894609/39894609" /> <InstanceDescription> <Title>Fácil
y resultón: Episodio 63</Title> <Genre
href="urn:miviewtv:cs:GenreCS:2007:0.3"> <Name>Cocina</Name> </Genre> <ParentalGuidance>
<mpeg7:ParentalRating
href="urn:dvb:metadata:cs:ParentalGuidanceCS:2007:2"> <mpeg7:Name>Suitable
for all audiences</mpeg7:Name> </mpeg7:ParentalRating> </ParentalGuidance>
</InstanceDescription> <PublishedStartTime>2015-03-26T16:30:00.000Z</PublishedStartTime>
<PublishedDuration>PT30M</PublishedDuration> <ImmediateViewing
value="false" /> <NetworkRecordOperator>default|STOVER</NetworkRecordOperator>
<UserActionList> <mpeg7:ActionType> <mpeg7:Name>FastForward</mpeg7:Name> </mpeg7:ActionType>
</UserActionList> <EventStartTime>2015-03-26T16:30:00.000Z</EventStartTime>
<EventDuration>PT30M</EventDuration> </ScheduleEvent> <ScheduleEvent> <Program
crid="crid://imagenio.es/0/39894610/39894610" /> <InstanceDescription> <Title>Sor
Lucía: Episodio 20</Title> <Genre
href="urn:miviewtv:cs:GenreCS:2007:0.3"> <Name>Cocina</Name> </Genre> <ParentalGuidance>
<mpeg7:ParentalRating
href="urn:dvb:metadata:cs:ParentalGuidanceCS:2007:2"> <mpeg7:Name>Suitable
for all audiences</mpeg7:Name> </mpeg7:ParentalRating> </ParentalGuidance>
</InstanceDescription> <PublishedStartTime>2015-03-26T17:00:00.000Z</PublishedStartTime>
<PublishedDuration>PT30M</PublishedDuration> <ImmediateViewing
value="false" /> <NetworkRecordOperator>default|STOVER</NetworkRecordOperator>
<UserActionList> <mpeg7:ActionType> <mpeg7:Name>FastForward</mpeg7:Name> </mpeg7:ActionType>
</UserActionList> <EventStartTime>2015-03-26T17:00:00.000Z</EventStartTime>
<EventDuration>PT30M</EventDuration> </ScheduleEvent> <ScheduleEvent> <Program
crid="crid://imagenio.es/0/39894611/39894611" /> <InstanceDescription> <Title>Paul
y Nick de travesía gastronómica: Episodio 7</Title> <Genre
href="urn:miviewtv:cs:GenreCS:2007:0.3"> <Name>Cocina</Name> </Genre> <ParentalGuidance>
<mpeg7:ParentalRating
href="urn:dvb:metadata:cs:ParentalGuidanceCS:2007:2"> <mpeg7:Name>Suitable
for all audiences</mpeg7:Name> </mpeg7:ParentalRating> </ParentalGuidance>
</InstanceDescription> <PublishedStartTime>2015-03-26T17:30:00.000Z</PublishedStartTime>
<PublishedDuration>PT30M</PublishedDuration> <ImmediateViewing
value="false" /> <NetworkRecordOperator>default|STOVER</NetworkRecordOperator>
<UserActionList> <mpeg7:ActionType> <mpeg7:Name>FastForward</mpeg7:Name> </mpeg7:ActionType>
</UserActionList> <EventStartTime>2015-03-26T17:30:00.000Z</EventStartTime>
<EventDuration>PT30M</EventDuration> </ScheduleEvent> <ScheduleEvent> <Program
crid="crid://imagenio.es/0/39894612/39894612" /> <InstanceDescription> <Title>Cocinamos
contigo: Episodio 335</Title> <Genre
href="urn:miviewtv:cs:GenreCS:2007:0.3"> <Name>Cocina</Name> </Genre> <ParentalGuidance>
<mpeg7:ParentalRating
href="urn:dvb:metadata:cs:ParentalGuidanceCS:2007:2"> <mpeg7:Name>Suitable
for all audiences</mpeg7:Name> </mpeg7:ParentalRating> </ParentalGuidance>
</InstanceDescription> <PublishedStartTime>2015-03-26T18:00:00.000Z</PublishedStartTime>
<PublishedDuration>PT30M</PublishedDuration> <ImmediateViewing
value="false" /> <NetworkRecordOperator>default|STOVER</NetworkRecordOperator>
<UserActionList> <mpeg7:ActionType> <mpeg7:Name>FastForward</mpeg7:Name> </mpeg7:ActionType>
</UserActionList> <EventStartTime>2015-03-26T18:00:00.000Z</EventStartTime>
<EventDuration>PT30M</EventDuration> </ScheduleEvent> <ScheduleEvent> <Program
crid="crid://imagenio.es/0/39894613/39894613" /> <InstanceDescription> <Title>La
diosa de las especias: Almuerzo de mujeres</Title> <Genre
href="urn:miviewtv:cs:GenreCS:2007:0.3"> <Name>Cocina</Name> </Genre> <ParentalGuidance>
<mpeg7:ParentalRating
href="urn:dvb:metadata:cs:ParentalGuidanceCS:2007:2"> <mpeg7:Name>Suitable
for all audiences</mpeg7:Name> </mpeg7:ParentalRating> </ParentalGuidance>
</InstanceDescription> <PublishedStartTime>2015-03-26T18:30:00.000Z</PublishedStartTime>
<PublishedDuration>PT30M</PublishedDuration> <ImmediateViewing
value="false" /> <NetworkRecordOperator>default|STOVER</NetworkRecordOperator>
<UserActionList> <mpeg7:ActionType> <mpeg7:Name>FastForward</mpeg7:Name> </mpeg7:ActionType>
</UserActionList> <EventStartTime>2015-03-26T18:30:00.000Z</EventStartTime>
<EventDuration>PT30M</EventDuration> </ScheduleEvent> <ScheduleEvent> <Program
crid="crid://imagenio.es/0/39894614/39894614" /> <InstanceDescription> <Title>El
toque de Samantha: Episodio 41</Title> <Genre
href="urn:miviewtv:cs:GenreCS:2007:0.3"> <Name>Cocina</Name> </Genre> <ParentalGuidance>
<mpeg7:ParentalRating
href="urn:dvb:metadata:cs:ParentalGuidanceCS:2007:2"> <mpeg7:Name>Suitable
for all audiences</mpeg7:Name> </mpeg7:ParentalRating> </ParentalGuidance>
</InstanceDescription> <PublishedStartTime>2015-03-26T19:00:00.000Z</PublishedStartTime>
<PublishedDuration>PT30M</PublishedDuration> <ImmediateViewing
value="false" /> <NetworkRecordOperator>default|STOVER</NetworkRecordOperator>
<UserActionList> <mpeg7:ActionType> <mpeg7:Name>FastForward</mpeg7:Name> </mpeg7:ActionType>
</UserActionList> <EventStartTime>2015-03-26T19:00:00.000Z</EventStartTime>
<EventDuration>PT30M</EventDuration> </ScheduleEvent> <ScheduleEvent> <Program
crid="crid://imagenio.es/0/39894615/39894615" /> <InstanceDescription> <Title>Recetas
por 5 euros: Episodio 85</Title> <Genre
href="urn:miviewtv:cs:GenreCS:2007:0.3"> <Name>Cocina</Name> </Genre> <ParentalGuidance>
<mpeg7:ParentalRating
href="urn:dvb:metadata:cs:ParentalGuidanceCS:2007:2"> <mpeg7:Name>Suitable
for all audiences</mpeg7:Name> </mpeg7:ParentalRating> </ParentalGuidance>
</InstanceDescription> <PublishedStartTime>2015-03-26T19:30:00.000Z</PublishedStartTime>
<PublishedDuration>PT30M</PublishedDuration> <ImmediateViewing
value="false" /> <NetworkRecordOperator>default|STOVER</NetworkRecordOperator>
<UserActionList> <mpeg7:ActionType> <mpeg7:Name>FastForward</mpeg7:Name> </mpeg7:ActionType>
</UserActionList> <EventStartTime>2015-03-26T19:30:00.000Z</EventStartTime>
<EventDuration>PT30M</EventDuration> </ScheduleEvent> <ScheduleEvent> <Program
crid="crid://imagenio.es/0/39894616/39894616" /> <InstanceDescription> <Title>Los
22 minutos de Julius: Episodio 361</Title> <Genre
href="urn:miviewtv:cs:GenreCS:2007:0.3"> <Name>Cocina</Name> </Genre> <ParentalGuidance>
<mpeg7:ParentalRating
href="urn:dvb:metadata:cs:ParentalGuidanceCS:2007:2"> <mpeg7:Name>Suitable
for all audiences</mpeg7:Name> </mpeg7:ParentalRating> </ParentalGuidance>
</InstanceDescription> <PublishedStartTime>2015-03-26T20:00:00.000Z</PublishedStartTime>
<PublishedDuration>PT30M</PublishedDuration> <ImmediateViewing
value="false" /> <NetworkRecordOperator>default|STOVER</NetworkRecordOperator>
<UserActionList> <mpeg7:ActionType> <mpeg7:Name>FastForward</mpeg7:Name> </mpeg7:ActionType>
</UserActionList> <EventStartTime>2015-03-26T20:00:00.000Z</EventStartTime>
<EventDuration>PT30M</EventDuration> </ScheduleEvent> <ScheduleEvent> <Program
crid="crid://imagenio.es/0/39894617/39894617" /> <InstanceDescription> <Title>Fácil
y resultón: Episodio 63</Title> <Genre
href="urn:miviewtv:cs:GenreCS:2007:0.3"> <Name>Cocina</Name> </Genre> <ParentalGuidance>
<mpeg7:ParentalRating
href="urn:dvb:metadata:cs:ParentalGuidanceCS:2007:2"> <mpeg7:Name>Suitable
for all audiences</mpeg7:Name> </mpeg7:ParentalRating> </ParentalGuidance>
</InstanceDescription> <PublishedStartTime>2015-03-26T20:30:00.000Z</PublishedStartTime>
<PublishedDuration>PT30M</PublishedDuration> <ImmediateViewing
value="false" /> <NetworkRecordOperator>default|STOVER</NetworkRecordOperator>
<UserActionList> <mpeg7:ActionType> <mpeg7:Name>FastForward</mpeg7:Name> </mpeg7:ActionType>
</UserActionList> <EventStartTime>2015-03-26T20:30:00.000Z</EventStartTime>
<EventDuration>PT30M</EventDuration> </ScheduleEvent> <ScheduleEvent> <Program
crid="crid://imagenio.es/0/39894618/39894618" /> <InstanceDescription> <Title>Destino:
Croacia; De la mano de: Neven Pelicaric: Episodio 1</Title> <Genre
href="urn:miviewtv:cs:GenreCS:2007:0.3"> <Name>Cocina</Name> </Genre> <ParentalGuidance>
<mpeg7:ParentalRating
href="urn:dvb:metadata:cs:ParentalGuidanceCS:2007:2"> <mpeg7:Name>Suitable
for all audiences</mpeg7:Name> </mpeg7:ParentalRating> </ParentalGuidance>
</InstanceDescription> <PublishedStartTime>2015-03-26T21:00:00.000Z</PublishedStartTime>
<PublishedDuration>PT30M</PublishedDuration> <ImmediateViewing
value="false" /> <NetworkRecordOperator>default|STOVER</NetworkRecordOperator>
<UserActionList> <mpeg7:ActionType> <mpeg7:Name>FastForward</mpeg7:Name> </mpeg7:ActionType>
</UserActionList> <EventStartTime>2015-03-26T21:00:00.000Z</EventStartTime>
<EventDuration>PT30M</EventDuration> </ScheduleEvent> <ScheduleEvent> <Program
crid="crid://imagenio.es/0/39894619/39894619" /> <InstanceDescription> <Title>El
rey del pincho: Episodio 19</Title> <Genre
href="urn:miviewtv:cs:GenreCS:2007:0.3"> <Name>Cocina</Name> </Genre> <ParentalGuidance>
<mpeg7:ParentalRating
href="urn:dvb:metadata:cs:ParentalGuidanceCS:2007:2"> <mpeg7:Name>Suitable
for all audiences</mpeg7:Name> </mpeg7:ParentalRating> </ParentalGuidance>
</InstanceDescription> <PublishedStartTime>2015-03-26T21:30:00.000Z</PublishedStartTime>
<PublishedDuration>PT30M</PublishedDuration> <ImmediateViewing
value="false" /> <NetworkRecordOperator>default|STOVER</NetworkRecordOperator>
<UserActionList> <mpeg7:ActionType> <mpeg7:Name>FastForward</mpeg7:Name> </mpeg7:ActionType>
</UserActionList> <EventStartTime>2015-03-26T21:30:00.000Z</EventStartTime>
<EventDuration>PT30M</EventDuration> </ScheduleEvent> <ScheduleEvent> <Program
crid="crid://imagenio.es/0/39894620/39894620" /> <InstanceDescription> <Title>Canal
Cocina recomienda: Episodio 7</Title> <Genre
href="urn:miviewtv:cs:GenreCS:2007:0.3"> <Name>Cocina</Name> </Genre> <ParentalGuidance>
<mpeg7:ParentalRating
href="urn:dvb:metadata:cs:ParentalGuidanceCS:2007:2"> <mpeg7:Name>Suitable
for all audiences</mpeg7:Name> </mpeg7:ParentalRating> </ParentalGuidance>
</InstanceDescription> <PublishedStartTime>2015-03-26T22:00:00.000Z</PublishedStartTime>
<PublishedDuration>PT30M</PublishedDuration> <ImmediateViewing
value="false" /> <NetworkRecordOperator>default|STOVER</NetworkRecordOperator>
<UserActionList> <mpeg7:ActionType> <mpeg7:Name>FastForward</mpeg7:Name> </mpeg7:ActionType>
</UserActionList> <EventStartTime>2015-03-26T22:00:00.000Z</EventStartTime>
<EventDuration>PT30M</EventDuration> </ScheduleEvent> <ScheduleEvent> <Program
crid="crid://imagenio.es/0/39894621/39894621" /> <InstanceDescription> <Title>Paul
y Nick de travesía gastronómica: Episodio 7</Title> <Genre
href="urn:miviewtv:cs:GenreCS:2007:0.3"> <Name>Cocina</Name> </Genre> <ParentalGuidance>
<mpeg7:ParentalRating
href="urn:dvb:metadata:cs:ParentalGuidanceCS:2007:2"> <mpeg7:Name>Suitable
for all audiences</mpeg7:Name> </mpeg7:ParentalRating> </ParentalGuidance>
</InstanceDescription> <PublishedStartTime>2015-03-26T22:30:00.000Z</PublishedStartTime>
<PublishedDuration>PT30M</PublishedDuration> <ImmediateViewing
value="false" /> <NetworkRecordOperator>default|STOVER</NetworkRecordOperator>
<UserActionList> <mpeg7:ActionType> <mpeg7:Name>FastForward</mpeg7:Name> </mpeg7:ActionType>
</UserActionList> <EventStartTime>2015-03-26T22:30:00.000Z</EventStartTime>
<EventDuration>PT30M</EventDuration> </ScheduleEvent> <ScheduleEvent> <Program
crid="crid://imagenio.es/0/39894622/39894622" /> <InstanceDescription> <Title>El
toque de Samantha: Episodio 41</Title> <Genre
href="urn:miviewtv:cs:GenreCS:2007:0.3"> <Name>Cocina</Name> </Genre> <ParentalGuidance>
<mpeg7:ParentalRating
href="urn:dvb:metadata:cs:ParentalGuidanceCS:2007:2"> <mpeg7:Name>Suitable
for all audiences</mpeg7:Name> </mpeg7:ParentalRating> </ParentalGuidance>
</InstanceDescription> <PublishedStartTime>2015-03-26T23:00:00.000Z</PublishedStartTime>
<PublishedDuration>PT30M</PublishedDuration> <ImmediateViewing
value="false" /> <NetworkRecordOperator>default|STOVER</NetworkRecordOperator>
<UserActionList> <mpeg7:ActionType> <mpeg7:Name>FastForward</mpeg7:Name> </mpeg7:ActionType>
</UserActionList> <EventStartTime>2015-03-26T23:00:00.000Z</EventStartTime>
<EventDuration>PT30M</EventDuration> </ScheduleEvent> <ScheduleEvent> <Program
crid="crid://imagenio.es/0/39894623/39894623" /> <InstanceDescription> <Title>La
cocina de Nicola: Episodio 39</Title> <Genre
href="urn:miviewtv:cs:GenreCS:2007:0.3"> <Name>Cocina</Name> </Genre> <ParentalGuidance>
<mpeg7:ParentalRating
href="urn:dvb:metadata:cs:ParentalGuidanceCS:2007:2"> <mpeg7:Name>Suitable
for all audiences</mpeg7:Name> </mpeg7:ParentalRating> </ParentalGuidance>
</InstanceDescription> <PublishedStartTime>2015-03-26T23:30:00.000Z</PublishedStartTime>
<PublishedDuration>PT30M</PublishedDuration> <ImmediateViewing
value="false" /> <NetworkRecordOperator>default|STOVER</NetworkRecordOperator>
<UserActionList> <mpeg7:ActionType> <mpeg7:Name>FastForward</mpeg7:Name> </mpeg7:ActionType>
</UserActionList> <EventStartTime>2015-03-26T23:30:00.000Z</EventStartTime>
<EventDuration>PT30M</EventDuration> </ScheduleEvent> </Schedule> </ProgramLocationTable>
</ProgramDescription> </TVAMain>